debouncer.v
//Early draft - I think we can do better than this!!
module debouncer (
	input clk,
	input sig,
	input reset,
	input [26:0] T_DEBOUNCE_cycles,
	output reg stable_out
);
	reg [26:0] counter;
	
	reg prev;

	always @(posedge clk) begin
		if (reset) begin
			prev <= 1'b0;
			stable_out <= 1'b0;
			counter <= 27'b0;
		end else if (prev == sig) begin
			counter <= counter + 1'b1;
		end else begin
			counter <= 1'b0;
		end
		
		if (counter > T_DEBOUNCE_cycles) begin
			stable_out <= sig;
			counter <= 1'b0;
		end
		prev <= sig;
	end

endmodule

debouncer_tb.v

`timescale 1ms/1us

module debouncer_tb;

    reg clk;
    reg sig;
    reg reset;
    reg [26:0] cycles;
    wire stable_out;

    // Instantiate the design under test
    debouncer dut (
        .clk        (clk),
        .sig        (sig),
        .reset      (reset),
	.T_DEBOUNCE_cycles	(cycles),
        .stable_out (stable_out)
    );

    // 100 MHz clock: 10 ns period
    initial clk = 1'b0;
    always #5 clk = ~clk;

    initial begin
        // Dump waveforms for GTKWave / your viewer of choice
        $dumpfile("debouncer_tb.vcd");
        $dumpvars(0, debouncer_tb);

        // Start with a clean reset
        sig   = 1'b0;
        reset = 1'b1;
	cycles = 10;
        #20;
        reset = 1'b0;

        // Simulate a bouncing button press: sig chatters before settling
        #10 sig = 1'b1;
        #10 sig = 1'b0;
        #10 sig = 1'b1;
        #10 sig = 1'b0;
        #10 sig = 1'b1;   // finally held high from here on

        // Hold steady long enough for the counter to cross the threshold.
        // At 10 ns/cycle, 300000 counts is ~3 ms of sim time.
        #3500;

        // Release the button and let it bounce again on the way down
        #10 sig = 1'b0;
        #10 sig = 1'b1;
        #10 sig = 1'b0;   // held low from here on

        #3500;

        $display("Simulation finished. Final stable_out = %b", stable_out);
        $finish;
    end

endmodule

debouncer_tb.vcd
$date
	Sat Jul 18 15:50:04 2026
$end
$version
	Questa Altera Starter FPGA Edition Version 2025.2
$end
$timescale
	1us
$end

$scope module debouncer_tb $end
$var reg 1 ! clk $end
$var reg 1 " sig $end
$var reg 1 # reset $end
$var reg 27 $ cycles [26:0] $end
$var wire 1 % stable_out $end

$scope module dut $end
$var wire 1 & clk $end
$var wire 1 ' sig $end
$var wire 1 ( reset $end
$var wire 1 ) T_DEBOUNCE_cycles [26] $end
$var wire 1 * T_DEBOUNCE_cycles [25] $end
$var wire 1 + T_DEBOUNCE_cycles [24] $end
$var wire 1 , T_DEBOUNCE_cycles [23] $end
$var wire 1 - T_DEBOUNCE_cycles [22] $end
$var wire 1 . T_DEBOUNCE_cycles [21] $end
$var wire 1 / T_DEBOUNCE_cycles [20] $end
$var wire 1 0 T_DEBOUNCE_cycles [19] $end
$var wire 1 1 T_DEBOUNCE_cycles [18] $end
$var wire 1 2 T_DEBOUNCE_cycles [17] $end
$var wire 1 3 T_DEBOUNCE_cycles [16] $end
$var wire 1 4 T_DEBOUNCE_cycles [15] $end
$var wire 1 5 T_DEBOUNCE_cycles [14] $end
$var wire 1 6 T_DEBOUNCE_cycles [13] $end
$var wire 1 7 T_DEBOUNCE_cycles [12] $end
$var wire 1 8 T_DEBOUNCE_cycles [11] $end
$var wire 1 9 T_DEBOUNCE_cycles [10] $end
$var wire 1 : T_DEBOUNCE_cycles [9] $end
$var wire 1 ; T_DEBOUNCE_cycles [8] $end
$var wire 1 < T_DEBOUNCE_cycles [7] $end
$var wire 1 = T_DEBOUNCE_cycles [6] $end
$var wire 1 > T_DEBOUNCE_cycles [5] $end
$var wire 1 ? T_DEBOUNCE_cycles [4] $end
$var wire 1 @ T_DEBOUNCE_cycles [3] $end
$var wire 1 A T_DEBOUNCE_cycles [2] $end
$var wire 1 B T_DEBOUNCE_cycles [1] $end
$var wire 1 C T_DEBOUNCE_cycles [0] $end
$var reg 1 D stable_out $end
$var reg 27 E counter [26:0] $end
$var reg 1 F prev $end
$upscope $end
$upscope $end
$enddefinitions $end
#0
$dumpvars
0!
0"
1#
b1010 $
xD
bx E
xF
x%
0C
1B
0A
1@
0?
0>
0=
0<
0;
0:
09
08
07
06
05
04
03
02
01
00
0/
0.
0-
0,
0+
0*
0)
1(
0'
0&
$end
#5000
1!
1&
0F
0D
b0 E
0%
#10000
0!
0&
#15000
1!
1&
#20000
0#
0!
0(
0&
#25000
1!
1&
b1 E
#30000
1"
0!
1'
0&
#35000
1!
1&
b0 E
1F
#40000
0"
0!
0'
0&
#45000
1!
1&
0F
#50000
1"
0!
1'
0&
#55000
1!
1&
1F
#60000
0"
0!
0'
0&
#65000
1!
1&
0F
#70000
1"
0!
1'
0&
#75000
1!
1&
1F
#80000
0!
0&
#85000
1!
1&
b1 E
#90000
0!
0&
#95000
1!
1&
b10 E
#100000
0!
0&
#105000
1!
1&
b11 E
#110000
0!
0&
#115000
1!
1&
b100 E
#120000
0!
0&
#125000
1!
1&
b101 E
#130000
0!
0&
#135000
1!
1&
b110 E
#140000
0!
0&
#145000
1!
1&
b111 E
#150000
0!
0&
#155000
1!
1&
b1000 E
#160000
0!
0&
#165000
1!
1&
b1001 E
#170000
0!
0&
#175000
1!
1&
b1010 E
#180000
0!
0&
#185000
1!
1&
b1011 E
#190000
0!
0&
#195000
1!
1&
b1100 E
1D
b0 E
1%
#200000
0!
0&
#205000
1!
1&
b1 E
#210000
0!
0&
#215000
1!
1&
b10 E
#220000
0!
0&
#225000
1!
1&
b11 E
#230000
0!
0&
#235000
1!
1&
b100 E
#240000
0!
0&
#245000
1!
1&
b101 E
#250000
0!
0&
#255000
1!
1&
b110 E
#260000
0!
0&
#265000
1!
1&
b111 E
#270000
0!
0&
#275000
1!
1&
b1000 E
#280000
0!
0&
#285000
1!
1&
b1001 E
#290000
0!
0&
#295000
1!
1&
b1010 E
#300000
0!
0&
#305000
1!
1&
b1011 E
#310000
0!
0&
#315000
1!
1&
b1100 E
b0 E
#320000
0!
0&
#325000
1!
1&
b1 E
#330000
0!
0&
#335000
1!
1&
b10 E
#340000
0!
0&
#345000
1!
1&
b11 E
#350000
0!
0&
#355000
1!
1&
b100 E
#360000
0!
0&
#365000
1!
1&
b101 E
#370000
0!
0&
#375000
1!
1&
b110 E
#380000
0!
0&
#385000
1!
1&
b111 E
#390000
0!
0&
#395000
1!
1&
b1000 E
#400000
0!
0&
#405000
1!
1&
b1001 E
#410000
0!
0&
#415000
1!
1&
b1010 E
#420000
0!
0&
#425000
1!
1&
b1011 E
#430000
0!
0&
#435000
1!
1&
b1100 E
b0 E
#440000
0!
0&
#445000
1!
1&
b1 E
#450000
0!
0&
#455000
1!
1&
b10 E
#460000
0!
0&
#465000
1!
1&
b11 E
#470000
0!
0&
#475000
1!
1&
b100 E
#480000
0!
0&
#485000
1!
1&
b101 E
#490000
0!
0&
#495000
1!
1&
b110 E
#500000
0!
0&
#505000
1!
1&
b111 E
#510000
0!
0&
#515000
1!
1&
b1000 E
#520000
0!
0&
#525000
1!
1&
b1001 E
#530000
0!
0&
#535000
1!
1&
b1010 E
#540000
0!
0&
#545000
1!
1&
b1011 E
#550000
0!
0&
#555000
1!
1&
b1100 E
b0 E
#560000
0!
0&
#565000
1!
1&
b1 E
#570000
0!
0&
#575000
1!
1&
b10 E
#580000
0!
0&
#585000
1!
1&
b11 E
#590000
0!
0&
#595000
1!
1&
b100 E
#600000
0!
0&
#605000
1!
1&
b101 E
#610000
0!
0&
#615000
1!
1&
b110 E
#620000
0!
0&
#625000
1!
1&
b111 E
#630000
0!
0&
#635000
1!
1&
b1000 E
#640000
0!
0&
#645000
1!
1&
b1001 E
#650000
0!
0&
#655000
1!
1&
b1010 E
#660000
0!
0&
#665000
1!
1&
b1011 E
#670000
0!
0&
#675000
1!
1&
b1100 E
b0 E
#680000
0!
0&
#685000
1!
1&
b1 E
#690000
0!
0&
#695000
1!
1&
b10 E
#700000
0!
0&
#705000
1!
1&
b11 E
#710000
0!
0&
#715000
1!
1&
b100 E
#720000
0!
0&
#725000
1!
1&
b101 E
#730000
0!
0&
#735000
1!
1&
b110 E
#740000
0!
0&
#745000
1!
1&
b111 E
#750000
0!
0&
#755000
1!
1&
b1000 E
#760000
0!
0&
#765000
1!
1&
b1001 E
#770000
0!
0&
#775000
1!
1&
b1010 E
#780000
0!
0&
#785000
1!
1&
b1011 E
#790000
0!
0&
#795000
1!
1&
b1100 E
b0 E
#800000
0!
0&
#805000
1!
1&
b1 E
#810000
0!
0&
#815000
1!
1&
b10 E
#820000
0!
0&
#825000
1!
1&
b11 E
#830000
0!
0&
#835000
1!
1&
b100 E
#840000
0!
0&
#845000
1!
1&
b101 E
#850000
0!
0&
#855000
1!
1&
b110 E
#860000
0!
0&
#865000
1!
1&
b111 E
#870000
0!
0&
#875000
1!
1&
b1000 E
#880000
0!
0&
#885000
1!
1&
b1001 E
#890000
0!
0&
#895000
1!
1&
b1010 E
#900000
0!
0&
#905000
1!
1&
b1011 E
#910000
0!
0&
#915000
1!
1&
b1100 E
b0 E
#920000
0!
0&
#925000
1!
1&
b1 E
#930000
0!
0&
#935000
1!
1&
b10 E
#940000
0!
0&
#945000
1!
1&
b11 E
#950000
0!
0&
#955000
1!
1&
b100 E
#960000
0!
0&
#965000
1!
1&
b101 E
#970000
0!
0&
#975000
1!
1&
b110 E
#980000
0!
0&
#985000
1!
1&
b111 E
#990000
0!
0&
#995000
1!
1&
b1000 E
#1000000
0!
0&
#1005000
1!
1&
b1001 E
#1010000
0!
0&
#1015000
1!
1&
b1010 E
#1020000
0!
0&
#1025000
1!
1&
b1011 E
#1030000
0!
0&
#1035000
1!
1&
b1100 E
b0 E
#1040000
0!
0&
#1045000
1!
1&
b1 E
#1050000
0!
0&
#1055000
1!
1&
b10 E
#1060000
0!
0&
#1065000
1!
1&
b11 E
#1070000
0!
0&
#1075000
1!
1&
b100 E
#1080000
0!
0&
#1085000
1!
1&
b101 E
#1090000
0!
0&
#1095000
1!
1&
b110 E
#1100000
0!
0&
#1105000
1!
1&
b111 E
#1110000
0!
0&
#1115000
1!
1&
b1000 E
#1120000
0!
0&
#1125000
1!
1&
b1001 E
#1130000
0!
0&
#1135000
1!
1&
b1010 E
#1140000
0!
0&
#1145000
1!
1&
b1011 E
#1150000
0!
0&
#1155000
1!
1&
b1100 E
b0 E
#1160000
0!
0&
#1165000
1!
1&
b1 E
#1170000
0!
0&
#1175000
1!
1&
b10 E
#1180000
0!
0&
#1185000
1!
1&
b11 E
#1190000
0!
0&
#1195000
1!
1&
b100 E
#1200000
0!
0&
#1205000
1!
1&
b101 E
#1210000
0!
0&
#1215000
1!
1&
b110 E
#1220000
0!
0&
#1225000
1!
1&
b111 E
#1230000
0!
0&
#1235000
1!
1&
b1000 E
#1240000
0!
0&
#1245000
1!
1&
b1001 E
#1250000
0!
0&
#1255000
1!
1&
b1010 E
#1260000
0!
0&
#1265000
1!
1&
b1011 E
#1270000
0!
0&
#1275000
1!
1&
b1100 E
b0 E
#1280000
0!
0&
#1285000
1!
1&
b1 E
#1290000
0!
0&
#1295000
1!
1&
b10 E
#1300000
0!
0&
#1305000
1!
1&
b11 E
#1310000
0!
0&
#1315000
1!
1&
b100 E
#1320000
0!
0&
#1325000
1!
1&
b101 E
#1330000
0!
0&
#1335000
1!
1&
b110 E
#1340000
0!
0&
#1345000
1!
1&
b111 E
#1350000
0!
0&
#1355000
1!
1&
b1000 E
#1360000
0!
0&
#1365000
1!
1&
b1001 E
#1370000
0!
0&
#1375000
1!
1&
b1010 E
#1380000
0!
0&
#1385000
1!
1&
b1011 E
#1390000
0!
0&
#1395000
1!
1&
b1100 E
b0 E
#1400000
0!
0&
#1405000
1!
1&
b1 E
#1410000
0!
0&
#1415000
1!
1&
b10 E
#1420000
0!
0&
#1425000
1!
1&
b11 E
#1430000
0!
0&
#1435000
1!
1&
b100 E
#1440000
0!
0&
#1445000
1!
1&
b101 E
#1450000
0!
0&
#1455000
1!
1&
b110 E
#1460000
0!
0&
#1465000
1!
1&
b111 E
#1470000
0!
0&
#1475000
1!
1&
b1000 E
#1480000
0!
0&
#1485000
1!
1&
b1001 E
#1490000
0!
0&
#1495000
1!
1&
b1010 E
#1500000
0!
0&
#1505000
1!
1&
b1011 E
#1510000
0!
0&
#1515000
1!
1&
b1100 E
b0 E
#1520000
0!
0&
#1525000
1!
1&
b1 E
#1530000
0!
0&
#1535000
1!
1&
b10 E
#1540000
0!
0&
#1545000
1!
1&
b11 E
#1550000
0!
0&
#1555000
1!
1&
b100 E
#1560000
0!
0&
#1565000
1!
1&
b101 E
#1570000
0!
0&
#1575000
1!
1&
b110 E
#1580000
0!
0&
#1585000
1!
1&
b111 E
#1590000
0!
0&
#1595000
1!
1&
b1000 E
#1600000
0!
0&
#1605000
1!
1&
b1001 E
#1610000
0!
0&
#1615000
1!
1&
b1010 E
#1620000
0!
0&
#1625000
1!
1&
b1011 E
#1630000
0!
0&
#1635000
1!
1&
b1100 E
b0 E
#1640000
0!
0&
#1645000
1!
1&
b1 E
#1650000
0!
0&
#1655000
1!
1&
b10 E
#1660000
0!
0&
#1665000
1!
1&
b11 E
#1670000
0!
0&
#1675000
1!
1&
b100 E
#1680000
0!
0&
#1685000
1!
1&
b101 E
#1690000
0!
0&
#1695000
1!
1&
b110 E
#1700000
0!
0&
#1705000
1!
1&
b111 E
#1710000
0!
0&
#1715000
1!
1&
b1000 E
#1720000
0!
0&
#1725000
1!
1&
b1001 E
#1730000
0!
0&
#1735000
1!
1&
b1010 E
#1740000
0!
0&
#1745000
1!
1&
b1011 E
#1750000
0!
0&
#1755000
1!
1&
b1100 E
b0 E
#1760000
0!
0&
#1765000
1!
1&
b1 E
#1770000
0!
0&
#1775000
1!
1&
b10 E
#1780000
0!
0&
#1785000
1!
1&
b11 E
#1790000
0!
0&
#1795000
1!
1&
b100 E
#1800000
0!
0&
#1805000
1!
1&
b101 E
#1810000
0!
0&
#1815000
1!
1&
b110 E
#1820000
0!
0&
#1825000
1!
1&
b111 E
#1830000
0!
0&
#1835000
1!
1&
b1000 E
#1840000
0!
0&
#1845000
1!
1&
b1001 E
#1850000
0!
0&
#1855000
1!
1&
b1010 E
#1860000
0!
0&
#1865000
1!
1&
b1011 E
#1870000
0!
0&
#1875000
1!
1&
b1100 E
b0 E
#1880000
0!
0&
#1885000
1!
1&
b1 E
#1890000
0!
0&
#1895000
1!
1&
b10 E
#1900000
0!
0&
#1905000
1!
1&
b11 E
#1910000
0!
0&
#1915000
1!
1&
b100 E
#1920000
0!
0&
#1925000
1!
1&
b101 E
#1930000
0!
0&
#1935000
1!
1&
b110 E
#1940000
0!
0&
#1945000
1!
1&
b111 E
#1950000
0!
0&
#1955000
1!
1&
b1000 E
#1960000
0!
0&
#1965000
1!
1&
b1001 E
#1970000
0!
0&
#1975000
1!
1&
b1010 E
#1980000
0!
0&
#1985000
1!
1&
b1011 E
#1990000
0!
0&
#1995000
1!
1&
b1100 E
b0 E
#2000000
0!
0&
#2005000
1!
1&
b1 E
#2010000
0!
0&
#2015000
1!
1&
b10 E
#2020000
0!
0&
#2025000
1!
1&
b11 E
#2030000
0!
0&
#2035000
1!
1&
b100 E
#2040000
0!
0&
#2045000
1!
1&
b101 E
#2050000
0!
0&
#2055000
1!
1&
b110 E
#2060000
0!
0&
#2065000
1!
1&
b111 E
#2070000
0!
0&
#2075000
1!
1&
b1000 E
#2080000
0!
0&
#2085000
1!
1&
b1001 E
#2090000
0!
0&
#2095000
1!
1&
b1010 E
#2100000
0!
0&
#2105000
1!
1&
b1011 E
#2110000
0!
0&
#2115000
1!
1&
b1100 E
b0 E
#2120000
0!
0&
#2125000
1!
1&
b1 E
#2130000
0!
0&
#2135000
1!
1&
b10 E
#2140000
0!
0&
#2145000
1!
1&
b11 E
#2150000
0!
0&
#2155000
1!
1&
b100 E
#2160000
0!
0&
#2165000
1!
1&
b101 E
#2170000
0!
0&
#2175000
1!
1&
b110 E
#2180000
0!
0&
#2185000
1!
1&
b111 E
#2190000
0!
0&
#2195000
1!
1&
b1000 E
#2200000
0!
0&
#2205000
1!
1&
b1001 E
#2210000
0!
0&
#2215000
1!
1&
b1010 E
#2220000
0!
0&
#2225000
1!
1&
b1011 E
#2230000
0!
0&
#2235000
1!
1&
b1100 E
b0 E
#2240000
0!
0&
#2245000
1!
1&
b1 E
#2250000
0!
0&
#2255000
1!
1&
b10 E
#2260000
0!
0&
#2265000
1!
1&
b11 E
#2270000
0!
0&
#2275000
1!
1&
b100 E
#2280000
0!
0&
#2285000
1!
1&
b101 E
#2290000
0!
0&
#2295000
1!
1&
b110 E
#2300000
0!
0&
#2305000
1!
1&
b111 E
#2310000
0!
0&
#2315000
1!
1&
b1000 E
#2320000
0!
0&
#2325000
1!
1&
b1001 E
#2330000
0!
0&
#2335000
1!
1&
b1010 E
#2340000
0!
0&
#2345000
1!
1&
b1011 E
#2350000
0!
0&
#2355000
1!
1&
b1100 E
b0 E
#2360000
0!
0&
#2365000
1!
1&
b1 E
#2370000
0!
0&
#2375000
1!
1&
b10 E
#2380000
0!
0&
#2385000
1!
1&
b11 E
#2390000
0!
0&
#2395000
1!
1&
b100 E
#2400000
0!
0&
#2405000
1!
1&
b101 E
#2410000
0!
0&
#2415000
1!
1&
b110 E
#2420000
0!
0&
#2425000
1!
1&
b111 E
#2430000
0!
0&
#2435000
1!
1&
b1000 E
#2440000
0!
0&
#2445000
1!
1&
b1001 E
#2450000
0!
0&
#2455000
1!
1&
b1010 E
#2460000
0!
0&
#2465000
1!
1&
b1011 E
#2470000
0!
0&
#2475000
1!
1&
b1100 E
b0 E
#2480000
0!
0&
#2485000
1!
1&
b1 E
#2490000
0!
0&
#2495000
1!
1&
b10 E
#2500000
0!
0&
#2505000
1!
1&
b11 E
#2510000
0!
0&
#2515000
1!
1&
b100 E
#2520000
0!
0&
#2525000
1!
1&
b101 E
#2530000
0!
0&
#2535000
1!
1&
b110 E
#2540000
0!
0&
#2545000
1!
1&
b111 E
#2550000
0!
0&
#2555000
1!
1&
b1000 E
#2560000
0!
0&
#2565000
1!
1&
b1001 E
#2570000
0!
0&
#2575000
1!
1&
b1010 E
#2580000
0!
0&
#2585000
1!
1&
b1011 E
#2590000
0!
0&
#2595000
1!
1&
b1100 E
b0 E
#2600000
0!
0&
#2605000
1!
1&
b1 E
#2610000
0!
0&
#2615000
1!
1&
b10 E
#2620000
0!
0&
#2625000
1!
1&
b11 E
#2630000
0!
0&
#2635000
1!
1&
b100 E
#2640000
0!
0&
#2645000
1!
1&
b101 E
#2650000
0!
0&
#2655000
1!
1&
b110 E
#2660000
0!
0&
#2665000
1!
1&
b111 E
#2670000
0!
0&
#2675000
1!
1&
b1000 E
#2680000
0!
0&
#2685000
1!
1&
b1001 E
#2690000
0!
0&
#2695000
1!
1&
b1010 E
#2700000
0!
0&
#2705000
1!
1&
b1011 E
#2710000
0!
0&
#2715000
1!
1&
b1100 E
b0 E
#2720000
0!
0&
#2725000
1!
1&
b1 E
#2730000
0!
0&
#2735000
1!
1&
b10 E
#2740000
0!
0&
#2745000
1!
1&
b11 E
#2750000
0!
0&
#2755000
1!
1&
b100 E
#2760000
0!
0&
#2765000
1!
1&
b101 E
#2770000
0!
0&
#2775000
1!
1&
b110 E
#2780000
0!
0&
#2785000
1!
1&
b111 E
#2790000
0!
0&
#2795000
1!
1&
b1000 E
#2800000
0!
0&
#2805000
1!
1&
b1001 E
#2810000
0!
0&
#2815000
1!
1&
b1010 E
#2820000
0!
0&
#2825000
1!
1&
b1011 E
#2830000
0!
0&
#2835000
1!
1&
b1100 E
b0 E
#2840000
0!
0&
#2845000
1!
1&
b1 E
#2850000
0!
0&
#2855000
1!
1&
b10 E
#2860000
0!
0&
#2865000
1!
1&
b11 E
#2870000
0!
0&
#2875000
1!
1&
b100 E
#2880000
0!
0&
#2885000
1!
1&
b101 E
#2890000
0!
0&
#2895000
1!
1&
b110 E
#2900000
0!
0&
#2905000
1!
1&
b111 E
#2910000
0!
0&
#2915000
1!
1&
b1000 E
#2920000
0!
0&
#2925000
1!
1&
b1001 E
#2930000
0!
0&
#2935000
1!
1&
b1010 E
#2940000
0!
0&
#2945000
1!
1&
b1011 E
#2950000
0!
0&
#2955000
1!
1&
b1100 E
b0 E
#2960000
0!
0&
#2965000
1!
1&
b1 E
#2970000
0!
0&
#2975000
1!
1&
b10 E
#2980000
0!
0&
#2985000
1!
1&
b11 E
#2990000
0!
0&
#2995000
1!
1&
b100 E
#3000000
0!
0&
#3005000
1!
1&
b101 E
#3010000
0!
0&
#3015000
1!
1&
b110 E
#3020000
0!
0&
#3025000
1!
1&
b111 E
#3030000
0!
0&
#3035000
1!
1&
b1000 E
#3040000
0!
0&
#3045000
1!
1&
b1001 E
#3050000
0!
0&
#3055000
1!
1&
b1010 E
#3060000
0!
0&
#3065000
1!
1&
b1011 E
#3070000
0!
0&
#3075000
1!
1&
b1100 E
b0 E
#3080000
0!
0&
#3085000
1!
1&
b1 E
#3090000
0!
0&
#3095000
1!
1&
b10 E
#3100000
0!
0&
#3105000
1!
1&
b11 E
#3110000
0!
0&
#3115000
1!
1&
b100 E
#3120000
0!
0&
#3125000
1!
1&
b101 E
#3130000
0!
0&
#3135000
1!
1&
b110 E
#3140000
0!
0&
#3145000
1!
1&
b111 E
#3150000
0!
0&
#3155000
1!
1&
b1000 E
#3160000
0!
0&
#3165000
1!
1&
b1001 E
#3170000
0!
0&
#3175000
1!
1&
b1010 E
#3180000
0!
0&
#3185000
1!
1&
b1011 E
#3190000
0!
0&
#3195000
1!
1&
b1100 E
b0 E
#3200000
0!
0&
#3205000
1!
1&
b1 E
#3210000
0!
0&
#3215000
1!
1&
b10 E
#3220000
0!
0&
#3225000
1!
1&
b11 E
#3230000
0!
0&
#3235000
1!
1&
b100 E
#3240000
0!
0&
#3245000
1!
1&
b101 E
#3250000
0!
0&
#3255000
1!
1&
b110 E
#3260000
0!
0&
#3265000
1!
1&
b111 E
#3270000
0!
0&
#3275000
1!
1&
b1000 E
#3280000
0!
0&
#3285000
1!
1&
b1001 E
#3290000
0!
0&
#3295000
1!
1&
b1010 E
#3300000
0!
0&
#3305000
1!
1&
b1011 E
#3310000
0!
0&
#3315000
1!
1&
b1100 E
b0 E
#3320000
0!
0&
#3325000
1!
1&
b1 E
#3330000
0!
0&
#3335000
1!
1&
b10 E
#3340000
0!
0&
#3345000
1!
1&
b11 E
#3350000
0!
0&
#3355000
1!
1&
b100 E
#3360000
0!
0&
#3365000
1!
1&
b101 E
#3370000
0!
0&
#3375000
1!
1&
b110 E
#3380000
0!
0&
#3385000
1!
1&
b111 E
#3390000
0!
0&
#3395000
1!
1&
b1000 E
#3400000
0!
0&
#3405000
1!
1&
b1001 E
#3410000
0!
0&
#3415000
1!
1&
b1010 E
#3420000
0!
0&
#3425000
1!
1&
b1011 E
#3430000
0!
0&
#3435000
1!
1&
b1100 E
b0 E
#3440000
0!
0&
#3445000
1!
1&
b1 E
#3450000
0!
0&
#3455000
1!
1&
b10 E
#3460000
0!
0&
#3465000
1!
1&
b11 E
#3470000
0!
0&
#3475000
1!
1&
b100 E
#3480000
0!
0&
#3485000
1!
1&
b101 E
#3490000
0!
0&
#3495000
1!
1&
b110 E
#3500000
0!
0&
#3505000
1!
1&
b111 E
#3510000
0!
0&
#3515000
1!
1&
b1000 E
#3520000
0!
0&
#3525000
1!
1&
b1001 E
#3530000
0!
0&
#3535000
1!
1&
b1010 E
#3540000
0!
0&
#3545000
1!
1&
b1011 E
#3550000
0!
0&
#3555000
1!
1&
b1100 E
b0 E
#3560000
0!
0&
#3565000
1!
1&
b1 E
#3570000
0!
0&
#3575000
1!
1&
b10 E
#3580000
0"
0!
0'
0&
#3585000
1!
1&
b0 E
0F
#3590000
1"
0!
1'
0&
#3595000
1!
1&
1F
#3600000
0"
0!
0'
0&
#3605000
1!
1&
0F
#3610000
0!
0&
#3615000
1!
1&
b1 E
#3620000
0!
0&
#3625000
1!
1&
b10 E
#3630000
0!
0&
#3635000
1!
1&
b11 E
#3640000
0!
0&
#3645000
1!
1&
b100 E
#3650000
0!
0&
#3655000
1!
1&
b101 E
#3660000
0!
0&
#3665000
1!
1&
b110 E
#3670000
0!
0&
#3675000
1!
1&
b111 E
#3680000
0!
0&
#3685000
1!
1&
b1000 E
#3690000
0!
0&
#3695000
1!
1&
b1001 E
#3700000
0!
0&
#3705000
1!
1&
b1010 E
#3710000
0!
0&
#3715000
1!
1&
b1011 E
#3720000
0!
0&
#3725000
1!
1&
b1100 E
0D
b0 E
0%
#3730000
0!
0&
#3735000
1!
1&
b1 E
#3740000
0!
0&
#3745000
1!
1&
b10 E
#3750000
0!
0&
#3755000
1!
1&
b11 E
#3760000
0!
0&
#3765000
1!
1&
b100 E
#3770000
0!
0&
#3775000
1!
1&
b101 E
#3780000
0!
0&
#3785000
1!
1&
b110 E
#3790000
0!
0&
#3795000
1!
1&
b111 E
#3800000
0!
0&
#3805000
1!
1&
b1000 E
#3810000
0!
0&
#3815000
1!
1&
b1001 E
#3820000
0!
0&
#3825000
1!
1&
b1010 E
#3830000
0!
0&
#3835000
1!
1&
b1011 E
#3840000
0!
0&
#3845000
1!
1&
b1100 E
b0 E
#3850000
0!
0&
#3855000
1!
1&
b1 E
#3860000
0!
0&
#3865000
1!
1&
b10 E
#3870000
0!
0&
#3875000
1!
1&
b11 E
#3880000
0!
0&
#3885000
1!
1&
b100 E
#3890000
0!
0&
#3895000
1!
1&
b101 E
#3900000
0!
0&
#3905000
1!
1&
b110 E
#3910000
0!
0&
#3915000
1!
1&
b111 E
#3920000
0!
0&
#3925000
1!
1&
b1000 E
#3930000
0!
0&
#3935000
1!
1&
b1001 E
#3940000
0!
0&
#3945000
1!
1&
b1010 E
#3950000
0!
0&
#3955000
1!
1&
b1011 E
#3960000
0!
0&
#3965000
1!
1&
b1100 E
b0 E
#3970000
0!
0&
#3975000
1!
1&
b1 E
#3980000
0!
0&
#3985000
1!
1&
b10 E
#3990000
0!
0&
#3995000
1!
1&
b11 E
#4000000
0!
0&
#4005000
1!
1&
b100 E
#4010000
0!
0&
#4015000
1!
1&
b101 E
#4020000
0!
0&
#4025000
1!
1&
b110 E
#4030000
0!
0&
#4035000
1!
1&
b111 E
#4040000
0!
0&
#4045000
1!
1&
b1000 E
#4050000
0!
0&
#4055000
1!
1&
b1001 E
#4060000
0!
0&
#4065000
1!
1&
b1010 E
#4070000
0!
0&
#4075000
1!
1&
b1011 E
#4080000
0!
0&
#4085000
1!
1&
b1100 E
b0 E
#4090000
0!
0&
#4095000
1!
1&
b1 E
#4100000
0!
0&
#4105000
1!
1&
b10 E
#4110000
0!
0&
#4115000
1!
1&
b11 E
#4120000
0!
0&
#4125000
1!
1&
b100 E
#4130000
0!
0&
#4135000
1!
1&
b101 E
#4140000
0!
0&
#4145000
1!
1&
b110 E
#4150000
0!
0&
#4155000
1!
1&
b111 E
#4160000
0!
0&
#4165000
1!
1&
b1000 E
#4170000
0!
0&
#4175000
1!
1&
b1001 E
#4180000
0!
0&
#4185000
1!
1&
b1010 E
#4190000
0!
0&
#4195000
1!
1&
b1011 E
#4200000
0!
0&
#4205000
1!
1&
b1100 E
b0 E
#4210000
0!
0&
#4215000
1!
1&
b1 E
#4220000
0!
0&
#4225000
1!
1&
b10 E
#4230000
0!
0&
#4235000
1!
1&
b11 E
#4240000
0!
0&
#4245000
1!
1&
b100 E
#4250000
0!
0&
#4255000
1!
1&
b101 E
#4260000
0!
0&
#4265000
1!
1&
b110 E
#4270000
0!
0&
#4275000
1!
1&
b111 E
#4280000
0!
0&
#4285000
1!
1&
b1000 E
#4290000
0!
0&
#4295000
1!
1&
b1001 E
#4300000
0!
0&
#4305000
1!
1&
b1010 E
#4310000
0!
0&
#4315000
1!
1&
b1011 E
#4320000
0!
0&
#4325000
1!
1&
b1100 E
b0 E
#4330000
0!
0&
#4335000
1!
1&
b1 E
#4340000
0!
0&
#4345000
1!
1&
b10 E
#4350000
0!
0&
#4355000
1!
1&
b11 E
#4360000
0!
0&
#4365000
1!
1&
b100 E
#4370000
0!
0&
#4375000
1!
1&
b101 E
#4380000
0!
0&
#4385000
1!
1&
b110 E
#4390000
0!
0&
#4395000
1!
1&
b111 E
#4400000
0!
0&
#4405000
1!
1&
b1000 E
#4410000
0!
0&
#4415000
1!
1&
b1001 E
#4420000
0!
0&
#4425000
1!
1&
b1010 E
#4430000
0!
0&
#4435000
1!
1&
b1011 E
#4440000
0!
0&
#4445000
1!
1&
b1100 E
b0 E
#4450000
0!
0&
#4455000
1!
1&
b1 E
#4460000
0!
0&
#4465000
1!
1&
b10 E
#4470000
0!
0&
#4475000
1!
1&
b11 E
#4480000
0!
0&
#4485000
1!
1&
b100 E
#4490000
0!
0&
#4495000
1!
1&
b101 E
#4500000
0!
0&
#4505000
1!
1&
b110 E
#4510000
0!
0&
#4515000
1!
1&
b111 E
#4520000
0!
0&
#4525000
1!
1&
b1000 E
#4530000
0!
0&
#4535000
1!
1&
b1001 E
#4540000
0!
0&
#4545000
1!
1&
b1010 E
#4550000
0!
0&
#4555000
1!
1&
b1011 E
#4560000
0!
0&
#4565000
1!
1&
b1100 E
b0 E
#4570000
0!
0&
#4575000
1!
1&
b1 E
#4580000
0!
0&
#4585000
1!
1&
b10 E
#4590000
0!
0&
#4595000
1!
1&
b11 E
#4600000
0!
0&
#4605000
1!
1&
b100 E
#4610000
0!
0&
#4615000
1!
1&
b101 E
#4620000
0!
0&
#4625000
1!
1&
b110 E
#4630000
0!
0&
#4635000
1!
1&
b111 E
#4640000
0!
0&
#4645000
1!
1&
b1000 E
#4650000
0!
0&
#4655000
1!
1&
b1001 E
#4660000
0!
0&
#4665000
1!
1&
b1010 E
#4670000
0!
0&
#4675000
1!
1&
b1011 E
#4680000
0!
0&
#4685000
1!
1&
b1100 E
b0 E
#4690000
0!
0&
