edgedetector.v

// Level or pulse? A debounced signal is still a level ? held high for as long as you hold the button. 
// If you toggle an LED on the level, it toggles every clock cycle while your finger is down. So you need 
// an edge detector: register the debounced signal, compare it to its previous value, emit a single-cycle 
// pulse on the 0?1 transition. Harris & Harris Interview Question 3.5 is exactly this circuit, which tells 
// you something about how often it comes up.

module edgedetector (
	input in,
	input clk,
	input reset,
	output reg pulse
);
	
	reg prev;
always @(posedge clk) begin
	if (reset) begin
		pulse <= 1'b0;
		prev <= 1'b0;
	end else begin
		pulse <= (prev != in);
		prev <= in;
	end
end
endmodule

edgedetector_tb.v

`timescale 1ms/1us

module edgedetector_tb;

    reg clk;
    reg reset;
    reg in;
    wire pulse;

    edgedetector dut (
	.in(in),
	.clk(clk),
	.reset(reset),
	.pulse(pulse)
);

    initial clk = 1'b0;
    always #5 clk = ~clk;

    initial begin
        // Dump waveforms for GTKWave / Questa
        $dumpfile("edgedetector_tb.vcd");
        $dumpvars(0, edgedetector_tb);
	
	in = 1'b0;
	reset = 1'b1;
	#20;
	reset = 1'b0;
	#12 in = 1'b1;
	#20 in = 1'b0;
	#40 in = 1'b1;
	#41 in = 1'b0;
	#6 in = 1'b1;
	#89 in = 1'b0;
	#10 in = 1'b1;
	#40 in = 1'b0;
	#50;
	$display("Simulation finished. Final sync_out = %b", pulse);
        $finish;
    end
    
endmodule

edgedetector_tb.vcd
$date
	Sun Jul 19 21:42:24 2026
$end
$version
	Questa Altera Starter FPGA Edition Version 2025.2
$end
$timescale
	1us
$end

$scope module edgedetector_tb $end
$var reg 1 ! clk $end
$var reg 1 " reset $end
$var reg 1 # in $end
$var wire 1 $ pulse $end

$scope module dut $end
$var wire 1 % in $end
$var wire 1 & clk $end
$var wire 1 ' reset $end
$var reg 1 ( pulse $end
$var reg 1 ) prev $end
$upscope $end
$upscope $end
$enddefinitions $end
#0
$dumpvars
0!
1"
0#
x(
x)
x$
1'
0&
0%
$end
#5000
1!
1&
0(
0)
0$
#10000
0!
0&
#15000
1!
1&
#20000
0"
0!
0'
0&
#25000
1!
1&
#30000
0!
0&
#32000
1#
1%
#35000
1!
1&
1(
1)
1$
#40000
0!
0&
#45000
1!
1&
0(
0$
#50000
0!
0&
#52000
0#
0%
#55000
1!
1&
1(
0)
1$
#60000
0!
0&
#65000
1!
1&
0(
0$
#70000
0!
0&
#75000
1!
1&
#80000
0!
0&
#85000
1!
1&
#90000
0!
0&
#92000
1#
1%
#95000
1!
1&
1(
1)
1$
#100000
0!
0&
#105000
1!
1&
0(
0$
#110000
0!
0&
#115000
1!
1&
#120000
0!
0&
#125000
1!
1&
#130000
0!
0&
#133000
0#
0%
#135000
1!
1&
1(
0)
1$
#139000
1#
1%
#140000
0!
0&
#145000
1!
1&
1)
#150000
0!
0&
#155000
1!
1&
0(
0$
#160000
0!
0&
#165000
1!
1&
#170000
0!
0&
#175000
1!
1&
#180000
0!
0&
#185000
1!
1&
#190000
0!
0&
#195000
1!
1&
#200000
0!
0&
#205000
1!
1&
#210000
0!
0&
#215000
1!
1&
#220000
0!
0&
#225000
1!
1&
#228000
0#
0%
#230000
0!
0&
#235000
1!
1&
1(
0)
1$
#238000
1#
1%
#240000
0!
0&
#245000
1!
1&
1)
#250000
0!
0&
#255000
1!
1&
0(
0$
#260000
0!
0&
#265000
1!
1&
#270000
0!
0&
#275000
1!
1&
#278000
0#
0%
#280000
0!
0&
#285000
1!
1&
1(
0)
1$
#290000
0!
0&
#295000
1!
1&
0(
0$
