synchroniser.v

module synchroniser (
	input clk,
	input reset,
	input async_in,
	output reg sync_out
);
	reg Ds;

always @(posedge clk) begin
	if (reset) begin
		Ds <= 1'b0;
		sync_out<= 1'b0;
	end else begin
		Ds <= async_in;
		sync_out <= Ds;
	end
end
endmodule

synchroniser_tb.v

`timescale 1ns/1ps

module synchroniser_tb;

    reg clk;
    reg reset;
    reg async_in;
    wire sync_out;

    // Instantiate the design under test
    synchroniser dut (
        .clk      (clk),
        .reset    (reset),
        .async_in (async_in),
        .sync_out (sync_out)
    );

    // 100 MHz clock: 10 ns period
    initial clk = 1'b0;
    always #5 clk = ~clk;

    initial begin
        // Dump waveforms for GTKWave / Questa
        $dumpfile("synchroniser_tb.vcd");
        $dumpvars(0, synchroniser_tb);

        // Clean reset
        async_in = 1'b0;
        reset    = 1'b1;
        #20;
        reset    = 1'b0;

        // Drive async_in at deliberately "off-beat" times (not multiples of 10 ns)
        // so it lands between clock edges, like a real asynchronous input.
        // sync_out should follow each change two rising edges later.
        #13 async_in = 1'b1;
        #27 async_in = 1'b0;
        #11 async_in = 1'b1;
        #33 async_in = 1'b0;
        #17 async_in = 1'b1;

        // Let it settle, then finish
        #100;

        $display("Simulation finished. Final sync_out = %b", sync_out);
        $finish;
    end

endmodule

synchroniser_tb.vcd
$date
	Wed Jul 15 23:03:26 2026
$end
$version
	Questa Altera Starter FPGA Edition Version 2025.2
$end
$timescale
	1ps
$end

$scope module synchroniser_tb $end
$var reg 1 ! clk $end
$var reg 1 " reset $end
$var reg 1 # async_in $end
$var wire 1 $ sync_out $end

$scope module dut $end
$var wire 1 % clk $end
$var wire 1 & reset $end
$var wire 1 ' async_in $end
$var reg 1 ( sync_out $end
$var reg 1 ) Ds $end
$upscope $end
$upscope $end
$enddefinitions $end
#0
$dumpvars
0!
1"
0#
x(
x)
x$
0'
1&
0%
$end
#5000
1!
1%
0)
0(
0$
#10000
0!
0%
#15000
1!
1%
#20000
0"
0!
0&
0%
#25000
1!
1%
#30000
0!
0%
#33000
1#
1'
#35000
1!
1%
1)
#40000
0!
0%
#45000
1!
1%
1(
1$
#50000
0!
0%
#55000
1!
1%
#60000
0#
0!
0'
0%
#65000
1!
1%
0)
#70000
0!
0%
#71000
1#
1'
#75000
1!
1%
1)
0(
0$
#80000
0!
0%
#85000
1!
1%
1(
1$
#90000
0!
0%
#95000
1!
1%
#100000
0!
0%
#104000
0#
0'
#105000
1!
1%
0)
#110000
0!
0%
#115000
1!
1%
0(
0$
#120000
0!
0%
#121000
1#
1'
#125000
1!
1%
1)
#130000
0!
0%
#135000
1!
1%
1(
1$
